{"status":"success","data":{"movieDetails":{"movieId":10,"movie":{"movieId":10,"tmdbMovieId":710,"imdbMovieId":"0113189","title":"GoldenEye","originalTitle":"GoldenEye","mpaa":"PG-13","runtime":130,"releaseDate":"1995-11-16","dvdReleaseDate":"2002-10-22","genres":["Adventure","Action","Thriller"],"languages":["English","Pусский","Español"],"directors":["Martin Campbell"],"actors":["Pierce Brosnan","Izabella Scorupco","Famke Janssen","Sean Bean","Joe Don Baker","Judi Dench","Robbie Coltrane","Tchéky Karyo","Gottfried John","Alan Cumming","Desmond Llewelyn","Samantha Bond","Michael Kitchen","Serena Gordon","Simon Kunz","Pavel Douglas","Olivier Lajous","Billy J. Mitchell","Constantine Gregory","Minnie Driver","Michelle Arthur","Ravil Isyanov","Vladimir Milanovich","Trevor Byfield","Peter Majer","Kate Gayson","Simone Bechtel"],"posterPath":"/47N9UR9ZGy0yWbj1m3vk26k2YQ9.jpg","backdropPaths":["/8o9FsYGpQgRrpASU38L4gcgxchw.jpg","/5jVWJiPpmk216Q7vjjlwNXXE6ee.jpg","/dtzJs7Ru1QQ72kZcg7DYIPzjB0z.jpg","/vm7yMg7YiYisMSeO3mUC5NUKbSB.jpg","/mifzRCLphhz1KLx5Mev22oe7C5N.jpg","/mRCbnW0etR9UcL7OFFZudTAf56y.jpg","/zIOG3SV5OTa0J0RMEekQ82GZQdU.jpg","/pqRI3H1iwJ34zL2eyjtQ1yFoH7e.jpg","/abTZc3nlTzyHwIqE36mLC8VptSp.jpg","/8whmi4TBWfo1lLdmfW0jztufbcu.jpg","/fc0Gm1KPZAIu5B6jw6BAlhqZnL9.jpg","/dBGpOXlNW8sHqRv8SuVE1rNgPPV.jpg","/jv0ciQsmP60xeSwP2Yycy4Y1ZvE.jpg","/fIWsCpYR9iGDMSbMTSAzy8L7Kg5.jpg","/xDoe5f33DEogUoMYPKFGKUMR3pE.jpg","/i9KqxGYc19ByiApMvFaWVKUmBYC.jpg","/3Csy6WMl4KCSGIimnRDFjf9jebX.jpg","/3qndbk23Huf9DWQIbI3NLi3xGKq.jpg","/35ndsAWls71pLpin0VftdZijsLP.jpg","/xAEyWTp23ntxDbzsQdtQYHFjhfz.jpg","/xi83aieHmPfCuKijfCiqS58Z5X5.jpg","/vASlOLza6rMUGUZzbVF5r8XCZ2k.jpg","/vr0jlAeHgqg782Lxqtqn25L8OQu.jpg","/rKsrhtWwmPwFQAF8aiZSOWMI8V4.jpg","/6BS2fMpfo2n88QBYzBaVJnvtL0J.jpg","/ep8f2zcbJ0UXBe7HfeUxr1Att7C.jpg","/dfVoWM8faS7tb3zhfcAafe4pIbK.jpg","/enjNQyhAAA11bDhJFh2phjdIeuP.jpg","/gUDLnHAlw1X3oTpOzpyyE8FiH5f.jpg","/e99W0JmSq2IaGmrAgy431UTIkkr.jpg","/2NpRnwAc8Kp83XmkqnYYUhOKi8i.jpg","/ruFyPcUT9X1AfRoCInL71VAThPK.jpg","/u6BXt1LtFmqomH3pgBXL33Eig3y.jpg","/gdhPU4KwyAIzbjKU7FBGNf3hTBe.jpg","/lcPXJy5K4uzP4rZXAsLrBG5ze4E.jpg","/iJZqSDEI63UjWqdMIyq2hoeO0sU.jpg","/tfcxnFU7buVorMihOR7lfZTnd3c.jpg","/yP1CwgCzEC4iry4Y17XdT9z3vXk.jpg"],"youtubeTrailerIds":["_PMD6YenOEg"],"plotSummary":"When a powerful satellite system falls into the hands of Alec Trevelyan, AKA Agent 006, a former ally-turned-enemy, only James Bond can save the world from a dangerous space weapon that -- in one short pulse -- could destroy the earth! As Bond squares off against his former compatriot, he also battles Xenia Onatopp, an assassin who uses pleasure as her ultimate weapon","numRatings":34971,"avgRating":3.4341,"releaseYear":"1995"},"movieUserData":{"userId":392087,"movieId":10,"rating":null,"dateRated":null,"prediction":3.4020486145929083,"wishlist":false,"hidden":false,"predictionDetails":{"primaryPrediction":3.4020486145929083,"primaryPredictionType":"USER","components":[{"pred":3.4020486145929083,"type":"USER"},{"pred":3.4341771500443548,"type":"FALLBACK"}]}}}}}